dustapprox/__init__.py
dustapprox/extinction.py
dustapprox/version.py
dustapprox/data/Fitz19_EDR3_extinctionlawcoefficients/Fitz19_EDR3_HRDTop.csv
dustapprox/data/Fitz19_EDR3_extinctionlawcoefficients/Fitz19_EDR3_MainSequence.csv
dustapprox/data/Gaia2/C1B431.csv
dustapprox/data/Gaia2/C1B556.csv
dustapprox/data/Gaia2/C1B655.csv
dustapprox/data/Gaia2/C1B768.csv
dustapprox/data/Gaia2/C1B916.csv
dustapprox/data/Gaia2/C1M326.csv
dustapprox/data/Gaia2/C1M344.csv
dustapprox/data/Gaia2/C1M379.csv
dustapprox/data/Gaia2/C1M395.csv
dustapprox/data/Gaia2/C1M410.csv
dustapprox/data/Gaia2/C1M467.csv
dustapprox/data/Gaia2/C1M506.csv
dustapprox/data/Gaia2/C1M515.csv
dustapprox/data/Gaia2/C1M549.csv
dustapprox/data/Gaia2/C1M656.csv
dustapprox/data/Gaia2/C1M716.csv
dustapprox/data/Gaia2/C1M747.csv
dustapprox/data/Gaia2/C1M825.csv
dustapprox/data/Gaia2/C1M861.csv
dustapprox/data/Gaia2/C1M965.csv
dustapprox/data/precomputed/README.rst
dustapprox/data/precomputed/polynomial/f99/kurucz/2mass_kurucz_f99_a0_teff.ecsv
dustapprox/data/precomputed/polynomial/f99/kurucz/gaia_kurucz_f99_a0_teff.ecsv
dustapprox/data/precomputed/polynomial/f99/kurucz/gaiac1_kurucz_f99_a0_teff.ecsv
dustapprox/data/precomputed/polynomial/f99/kurucz/galex_kurucz_f99_a0_teff.ecsv
dustapprox/data/precomputed/polynomial/f99/kurucz/generic_kurucz_f99_a0_teff.ecsv
dustapprox/data/precomputed/polynomial/f99/kurucz/sloan_kurucz_f99_a0_teff.ecsv
dustapprox/data/precomputed/polynomial/f99/kurucz/wise_kurucz_f99_a0_teff.ecsv
dustapprox/io/__init__.py
dustapprox/io/ecsv.py
dustapprox/io/svo.py
dustapprox/literature/__init__.py
dustapprox/literature/c1.py
dustapprox/literature/edr3.py
dustapprox/models/__init__.py
dustapprox/models/basemodel.py
dustapprox/models/polynomial.py
dustapprox/tools/__init__.py
dustapprox/tools/downloader.py
dustapprox/tools/grid.py
dustapprox/tools/parallel.py
dustapprox-0.1.dist-info/LICENSE
dustapprox-0.1.dist-info/METADATA
dustapprox-0.1.dist-info/WHEEL
dustapprox-0.1.dist-info/top_level.txt
dustapprox-0.1.dist-info/RECORD
