Metadata-Version: 2.1
Name: dustapprox
Version: 0.1
Summary: A tool for computing extinction coefficients in a quick and dirty manner
Home-page: https://github.com/mfouesneau/dustapprox
Author: Morgan Fouesneau
Author-email: 
License: UNKNOWN
Platform: UNKNOWN
Classifier: Intended Audience :: Science/Research
Classifier: Operating System :: OS Independent
Classifier: Programming Language :: Python :: 3
Classifier: License :: OSI Approved :: BSD License
Classifier: Topic :: Scientific/Engineering :: Astronomy
Requires-Python: >=3.6
License-File: LICENSE
Requires-Dist: numpy
Requires-Dist: scipy
Requires-Dist: pyphot
Requires-Dist: pyyaml
Requires-Dist: pandas
Requires-Dist: astropy
Requires-Dist: scikit-learn
Requires-Dist: tqdm
